swarmauri_tokens_dpopboundjwt/DPoPBoundJWTTokenService.py
swarmauri_tokens_dpopboundjwt/JWTTokenService.py
swarmauri_tokens_dpopboundjwt/__init__.py
swarmauri_tokens_dpopboundjwt-0.3.0.dev4.dist-info/LICENSE
swarmauri_tokens_dpopboundjwt-0.3.0.dev4.dist-info/METADATA
swarmauri_tokens_dpopboundjwt-0.3.0.dev4.dist-info/WHEEL
swarmauri_tokens_dpopboundjwt-0.3.0.dev4.dist-info/entry_points.txt
swarmauri_tokens_dpopboundjwt-0.3.0.dev4.dist-info/RECORD
